pytorch_sdk/__init__.py
pytorch_sdk-0.0.1.dist-info/LICENSE
pytorch_sdk-0.0.1.dist-info/METADATA
pytorch_sdk-0.0.1.dist-info/WHEEL
pytorch_sdk-0.0.1.dist-info/top_level.txt
pytorch_sdk-0.0.1.dist-info/RECORD
